AdaptFTIR/AdaptFTIR.py
AdaptFTIR/__init__.py
AdaptFTIR-0.1.0.dist-info/METADATA
AdaptFTIR-0.1.0.dist-info/WHEEL
AdaptFTIR-0.1.0.dist-info/top_level.txt
AdaptFTIR-0.1.0.dist-info/RECORD
