Metadata-Version: 2.1
Name: AdaptFTIR
Version: 0.1.0
Summary: Domain adaptation for FTIR spectra
Home-page: https://github.com/Niklas-LK/AdaptFTIR
Author: Niklas Leopold-Kerschbaumer
Author-email: niklas.leopold-kerschbaumer@hotmail.com
License: MIT
Requires-Dist: numpy
Requires-Dist: typing
